AUTHORS.rst
CONTRIBUTING.rst
HISTORY.rst
LICENSE
MANIFEST.in
README.rst
setup.cfg
setup.py
docs/Makefile
docs/authors.rst
docs/conf.py
docs/contributing.rst
docs/geo_python.rst
docs/history.rst
docs/index.rst
docs/installation.rst
docs/make.bat
docs/modules.rst
docs/readme.rst
docs/usage.rst
docs/_build/html/_static/ajax-loader.gif
docs/_build/html/_static/comment-bright.png
docs/_build/html/_static/comment-close.png
docs/_build/html/_static/comment.png
docs/_build/html/_static/down-pressed.png
docs/_build/html/_static/down.png
docs/_build/html/_static/file.png
docs/_build/html/_static/minus.png
docs/_build/html/_static/plus.png
docs/_build/html/_static/up-pressed.png
docs/_build/html/_static/up.png
geo_python/__init__.py
geo_python/exc.py
geo_python/geo_python.py
geo_python.egg-info/PKG-INFO
geo_python.egg-info/SOURCES.txt
geo_python.egg-info/dependency_links.txt
geo_python.egg-info/not-zip-safe
geo_python.egg-info/requires.txt
geo_python.egg-info/top_level.txt
tests/__init__.py
tests/test_geo_python.py