Metadata-Version: 1.1
Name: geo-python
Version: 0.1.1
Summary: Simple GEO library based on Redis GEO function
Home-page: https://github.com/jerryleooo/geo_python
Author: Jerry Lau
Author-email: whilgeek@gmail.com
License: MIT license
Keywords: geo_python
Platform: UNKNOWN
Classifier: Development Status :: 2 - Pre-Alpha
Classifier: Intended Audience :: Developers
Classifier: License :: OSI Approved :: MIT License
Classifier: Natural Language :: English
Classifier: Programming Language :: Python :: 2
Classifier: Programming Language :: Python :: 2.6
Classifier: Programming Language :: Python :: 2.7
Classifier: Programming Language :: Python :: 3
Classifier: Programming Language :: Python :: 3.3
Classifier: Programming Language :: Python :: 3.4
Classifier: Programming Language :: Python :: 3.5
